{"v":"5.10.0","fr":29.9700012207031,"ip":0,"op":91.000003706506,"w":174,"h":109,"nm":"レイヤー 1/Group 3","ddd":0,"assets":[],"layers":[{"ddd":0,"ind":1,"ty":4,"nm":"シェイプレイヤー 3","sr":1,"ks":{"o":{"a":0,"k":100,"ix":11},"r":{"a":0,"k":3,"ix":10},"p":{"a":0,"k":[89.5,69.75,0],"ix":2,"l":2},"a":{"a":0,"k":[0,0,0],"ix":1,"l":2},"s":{"a":0,"k":[100,100,100],"ix":6,"l":2}},"ao":0,"shapes":[{"ty":"gr","it":[{"ty":"rc","d":1,"s":{"a":0,"k":[1,9],"ix":2},"p":{"a":0,"k":[0,0],"ix":3},"r":{"a":0,"k":0,"ix":4},"nm":"長方形パス 1","mn":"ADBE Vector Shape - Rect","hd":false},{"ty":"fl","c":{"a":0,"k":[0.574693620205,0.529128015041,0.479765295982,1],"ix":4},"o":{"a":0,"k":100,"ix":5},"r":1,"bm":0,"nm":"塗り 1","mn":"ADBE Vector Graphic - Fill","hd":false},{"ty":"tr","p":{"a":1,"k":[{"i":{"x":0.667,"y":1},"o":{"x":0.333,"y":0},"t":74,"s":[73,11],"to":[1.667,-1.667],"ti":[-2.167,2.167]},{"i":{"x":0.667,"y":1},"o":{"x":0.333,"y":0},"t":79,"s":[83,1],"to":[2.167,-2.167],"ti":[-0.5,0.5]},{"t":83.0000033806593,"s":[86,-2]}],"ix":2},"a":{"a":0,"k":[0,0],"ix":1},"s":{"a":1,"k":[{"i":{"x":[0.833,0.833],"y":[1,1]},"o":{"x":[0.333,0.333],"y":[0,0]},"t":74,"s":[100,0]},{"i":{"x":[0.833,0.833],"y":[1,1]},"o":{"x":[0.167,0.167],"y":[0,0]},"t":79,"s":[99.952,100]},{"t":83.0000033806593,"s":[99.952,0]}],"ix":3},"r":{"a":0,"k":14437.518,"ix":6},"o":{"a":0,"k":100,"ix":7},"sk":{"a":0,"k":0,"ix":4},"sa":{"a":0,"k":0,"ix":5},"nm":"トランスフォーム"}],"nm":"グループ 1","np":2,"cix":2,"bm":0,"ix":1,"mn":"ADBE Vector Group","hd":false}],"ip":15.0000006109625,"op":914.000037227983,"st":15.0000006109625,"ct":1,"bm":0},{"ddd":0,"ind":2,"ty":4,"nm":"シェイプレイヤー 2","sr":1,"ks":{"o":{"a":0,"k":100,"ix":11},"r":{"a":0,"k":3,"ix":10},"p":{"a":0,"k":[89.5,59.75,0],"ix":2,"l":2},"a":{"a":0,"k":[0,0,0],"ix":1,"l":2},"s":{"a":0,"k":[100,100,100],"ix":6,"l":2}},"ao":0,"shapes":[{"ty":"gr","it":[{"ty":"rc","d":1,"s":{"a":0,"k":[1,9],"ix":2},"p":{"a":0,"k":[0,0],"ix":3},"r":{"a":0,"k":0,"ix":4},"nm":"長方形パス 1","mn":"ADBE Vector Shape - Rect","hd":false},{"ty":"fl","c":{"a":0,"k":[0.574693620205,0.529128015041,0.479765295982,1],"ix":4},"o":{"a":0,"k":100,"ix":5},"r":1,"bm":0,"nm":"塗り 1","mn":"ADBE Vector Graphic - Fill","hd":false},{"ty":"tr","p":{"a":1,"k":[{"i":{"x":0.667,"y":1},"o":{"x":0.333,"y":0},"t":74,"s":[73,11],"to":[1.667,-1.667],"ti":[-2.167,2.167]},{"i":{"x":0.667,"y":1},"o":{"x":0.333,"y":0},"t":79,"s":[83,1],"to":[2.167,-2.167],"ti":[-0.5,0.5]},{"t":83.0000033806593,"s":[86,-2]}],"ix":2},"a":{"a":0,"k":[0,0],"ix":1},"s":{"a":1,"k":[{"i":{"x":[0.833,0.833],"y":[1,1]},"o":{"x":[0.333,0.333],"y":[0,0]},"t":74,"s":[100,0]},{"i":{"x":[0.833,0.833],"y":[1,1]},"o":{"x":[0.167,0.167],"y":[0,0]},"t":79,"s":[99.952,100]},{"t":83.0000033806593,"s":[99.952,0]}],"ix":3},"r":{"a":0,"k":14437.518,"ix":6},"o":{"a":0,"k":100,"ix":7},"sk":{"a":0,"k":0,"ix":4},"sa":{"a":0,"k":0,"ix":5},"nm":"トランスフォーム"}],"nm":"グループ 1","np":2,"cix":2,"bm":0,"ix":1,"mn":"ADBE Vector Group","hd":false}],"ip":15.0000006109625,"op":914.000037227983,"st":15.0000006109625,"ct":1,"bm":0},{"ddd":0,"ind":3,"ty":4,"nm":"シェイプレイヤー 1","sr":1,"ks":{"o":{"a":0,"k":100,"ix":11},"r":{"a":0,"k":1,"ix":10},"p":{"a":0,"k":[87,54.5,0],"ix":2,"l":2},"a":{"a":0,"k":[0,0,0],"ix":1,"l":2},"s":{"a":0,"k":[100,100,100],"ix":6,"l":2}},"ao":0,"shapes":[{"ty":"gr","it":[{"ty":"rc","d":1,"s":{"a":0,"k":[1,9],"ix":2},"p":{"a":0,"k":[0,0],"ix":3},"r":{"a":0,"k":0,"ix":4},"nm":"長方形パス 1","mn":"ADBE Vector Shape - Rect","hd":false},{"ty":"fl","c":{"a":0,"k":[0.574693620205,0.529128015041,0.479765295982,1],"ix":4},"o":{"a":0,"k":100,"ix":5},"r":1,"bm":0,"nm":"塗り 1","mn":"ADBE Vector Graphic - Fill","hd":false},{"ty":"tr","p":{"a":1,"k":[{"i":{"x":0.667,"y":1},"o":{"x":0.333,"y":0},"t":74,"s":[73,11],"to":[1.667,-1.667],"ti":[-2.167,2.167]},{"i":{"x":0.667,"y":1},"o":{"x":0.333,"y":0},"t":79,"s":[83,1],"to":[2.167,-2.167],"ti":[-0.5,0.5]},{"t":83.0000033806593,"s":[86,-2]}],"ix":2},"a":{"a":0,"k":[0,0],"ix":1},"s":{"a":1,"k":[{"i":{"x":[0.833,0.833],"y":[1,1]},"o":{"x":[0.333,0.333],"y":[0,0]},"t":74,"s":[100,0]},{"i":{"x":[0.833,0.833],"y":[1,1]},"o":{"x":[0.167,0.167],"y":[0,0]},"t":79,"s":[99.952,100]},{"t":83.0000033806593,"s":[99.952,0]}],"ix":3},"r":{"a":0,"k":14437.518,"ix":6},"o":{"a":0,"k":100,"ix":7},"sk":{"a":0,"k":0,"ix":4},"sa":{"a":0,"k":0,"ix":5},"nm":"トランスフォーム"}],"nm":"グループ 1","np":2,"cix":2,"bm":0,"ix":1,"mn":"ADBE Vector Group","hd":false}],"ip":15.0000006109625,"op":914.000037227983,"st":15.0000006109625,"ct":1,"bm":0},{"ddd":0,"ind":4,"ty":4,"nm":"レイヤー 1/Group 3アウトライン","sr":1,"ks":{"o":{"a":0,"k":100,"ix":11},"r":{"a":0,"k":0,"ix":10},"p":{"a":0,"k":[87,54.5,0],"ix":2,"l":2},"a":{"a":0,"k":[87,54.5,0],"ix":1,"l":2},"s":{"a":0,"k":[100,100,100],"ix":6,"l":2}},"ao":0,"shapes":[{"ty":"gr","it":[{"ind":0,"ty":"sh","ix":1,"ks":{"a":0,"k":{"i":[[0,0],[0.924,2.231],[0,2.415],[-0.924,2.231],[-1.708,1.707],[-2.231,0.924],[-2.415,0],[-2.23,-0.924],[-1.708,-1.707],[0,0]],"o":[[-1.708,-1.708],[-0.924,-2.231],[0,-2.415],[0.924,-2.231],[1.707,-1.707],[2.231,-0.924],[2.415,0],[2.231,0.924],[0,0],[0,0]],"v":[[-10.309,15.695],[-14.295,9.73],[-15.695,2.693],[-14.295,-4.344],[-10.309,-10.309],[-4.344,-14.295],[2.693,-15.695],[9.729,-14.295],[15.695,-10.309],[2.693,2.693]],"c":true},"ix":2},"nm":"パス 1","mn":"ADBE Vector Shape - Group","hd":false},{"ty":"fl","c":{"a":0,"k":[0.435294147566,0.388235324037,0.337254901961,1],"ix":4},"o":{"a":0,"k":100,"ix":5},"r":1,"bm":0,"nm":"塗り 1","mn":"ADBE Vector Graphic - Fill","hd":false},{"ty":"tr","p":{"a":0,"k":[23.545,38.831],"ix":2},"a":{"a":0,"k":[-10.766,15.524],"ix":1},"s":{"a":1,"k":[{"i":{"x":[0.667,0.667],"y":[1,1]},"o":{"x":[0.333,0.333],"y":[0,0]},"t":0,"s":[0,0]},{"i":{"x":[0.667,0.667],"y":[1,1]},"o":{"x":[0.333,0.333],"y":[0,0]},"t":10,"s":[120,120]},{"t":13.0000005295009,"s":[100,100]}],"ix":3},"r":{"a":1,"k":[{"i":{"x":[0.667],"y":[1]},"o":{"x":[0.333],"y":[0]},"t":15,"s":[0]},{"i":{"x":[0.667],"y":[1]},"o":{"x":[0.333],"y":[0]},"t":19,"s":[-10]},{"i":{"x":[0.667],"y":[1]},"o":{"x":[0.333],"y":[0]},"t":23,"s":[0]},{"i":{"x":[0.667],"y":[1]},"o":{"x":[0.333],"y":[0]},"t":27,"s":[-10]},{"i":{"x":[0.667],"y":[1]},"o":{"x":[0.333],"y":[0]},"t":31,"s":[0]},{"i":{"x":[0.667],"y":[1]},"o":{"x":[0.167],"y":[0]},"t":35,"s":[-10]},{"t":39.0000015885026,"s":[0]}],"ix":6},"o":{"a":0,"k":100,"ix":7},"sk":{"a":0,"k":0,"ix":4},"sa":{"a":0,"k":0,"ix":5},"nm":"トランスフォーム"}],"nm":"グループ 6","np":2,"cix":2,"bm":0,"ix":1,"mn":"ADBE Vector Group","hd":false},{"ty":"gr","it":[{"ind":0,"ty":"sh","ix":1,"ks":{"a":0,"k":{"i":[[0,0],[-0.924,-2.231],[0,-2.415],[0.924,-2.231],[1.707,-1.708],[2.231,-0.924],[2.415,0],[2.231,0.924],[1.707,1.707],[0,0]],"o":[[1.707,1.707],[0.924,2.231],[0,2.415],[-0.924,2.231],[-1.708,1.707],[-2.231,0.924],[-2.415,0],[-2.231,-0.924],[0,0],[0,0]],"v":[[10.31,-15.695],[14.296,-9.73],[15.695,-2.693],[14.296,4.344],[10.31,10.309],[4.344,14.296],[-2.693,15.695],[-9.729,14.296],[-15.695,10.309],[-2.693,-2.693]],"c":true},"ix":2},"nm":"パス 1","mn":"ADBE Vector Shape - Group","hd":false},{"ty":"fl","c":{"a":0,"k":[0.729411764706,0.635294117647,0.501960784314,1],"ix":4},"o":{"a":0,"k":100,"ix":5},"r":1,"bm":0,"nm":"塗り 1","mn":"ADBE Vector Graphic - Fill","hd":false},{"ty":"tr","p":{"a":0,"k":[28.696,39.693],"ix":2},"a":{"a":0,"k":[0,0],"ix":1},"s":{"a":1,"k":[{"i":{"x":[0.667,0.667],"y":[1,1]},"o":{"x":[0.333,0.333],"y":[0,0]},"t":1,"s":[0,0]},{"i":{"x":[0.667,0.667],"y":[1,1]},"o":{"x":[0.333,0.333],"y":[0,0]},"t":11,"s":[120,120]},{"t":14.0000005702317,"s":[100,100]}],"ix":3},"r":{"a":0,"k":0,"ix":6},"o":{"a":0,"k":100,"ix":7},"sk":{"a":0,"k":0,"ix":4},"sa":{"a":0,"k":0,"ix":5},"nm":"トランスフォーム"}],"nm":"グループ 8","np":2,"cix":2,"bm":0,"ix":2,"mn":"ADBE Vector Group","hd":false},{"ty":"gr","it":[{"ind":0,"ty":"sh","ix":1,"ks":{"a":0,"k":{"i":[[-11.322,0],[0,-11.322],[11.322,0],[0,11.322]],"o":[[11.322,0],[0,11.322],[-11.322,0],[0,-11.322]],"v":[[0,-20.5],[20.5,0],[0,20.5],[-20.5,0]],"c":true},"ix":2},"nm":"パス 1","mn":"ADBE Vector Shape - Group","hd":false},{"ty":"fl","c":{"a":0,"k":[0.674509803922,0.466666696586,0.274509803922,1],"ix":4},"o":{"a":0,"k":100,"ix":5},"r":1,"bm":0,"nm":"塗り 1","mn":"ADBE Vector Graphic - Fill","hd":false},{"ty":"tr","p":{"a":0,"k":[69.5,36.5],"ix":2},"a":{"a":0,"k":[0,0],"ix":1},"s":{"a":1,"k":[{"i":{"x":[0.833,0.833],"y":[1,1]},"o":{"x":[0.333,0.333],"y":[0,0]},"t":7,"s":[0,0]},{"i":{"x":[0.833,0.833],"y":[1,1]},"o":{"x":[0.167,0.167],"y":[0,0]},"t":16,"s":[120,120]},{"i":{"x":[0.833,0.833],"y":[1,1]},"o":{"x":[0.167,0.167],"y":[0,0]},"t":19,"s":[100,100]},{"i":{"x":[0.833,0.833],"y":[1,1]},"o":{"x":[0.167,0.167],"y":[0,0]},"t":22,"s":[80,80]},{"i":{"x":[0.833,0.833],"y":[1,1]},"o":{"x":[0.167,0.167],"y":[0,0]},"t":25,"s":[100,100]},{"i":{"x":[0.833,0.833],"y":[1,1]},"o":{"x":[0.167,0.167],"y":[0,0]},"t":28,"s":[90,90]},{"t":31.0000012626559,"s":[100,100]}],"ix":3},"r":{"a":0,"k":0,"ix":6},"o":{"a":0,"k":100,"ix":7},"sk":{"a":0,"k":0,"ix":4},"sa":{"a":0,"k":0,"ix":5},"nm":"トランスフォーム"}],"nm":"グループ 11","np":2,"cix":2,"bm":0,"ix":3,"mn":"ADBE Vector Group","hd":false},{"ty":"gr","it":[{"ind":0,"ty":"sh","ix":1,"ks":{"a":0,"k":{"i":[[0,0],[0,0],[0,0],[0,0]],"o":[[0,0],[0,0],[0,0],[0,0]],"v":[[-6,-14.5],[6,-14.5],[6,14.5],[-6,14.5]],"c":true},"ix":2},"nm":"パス 1","mn":"ADBE Vector Shape - Group","hd":false},{"ty":"fl","c":{"a":0,"k":[0.674509803922,0.466666696586,0.274509803922,1],"ix":4},"o":{"a":0,"k":100,"ix":5},"r":1,"bm":0,"nm":"塗り 1","mn":"ADBE Vector Graphic - Fill","hd":false},{"ty":"tr","p":{"a":1,"k":[{"i":{"x":0.833,"y":1},"o":{"x":0.333,"y":0},"t":31,"s":[101,25.5],"to":[0,-0.833],"ti":[0,3.769]},{"i":{"x":0.667,"y":1},"o":{"x":0.333,"y":0},"t":33,"s":[101,20.5],"to":[0,-3.769],"ti":[0,-0.898]},{"i":{"x":0.667,"y":1},"o":{"x":0.333,"y":0},"t":37,"s":[101,2.889],"to":[0,0.898],"ti":[0,-2.935]},{"i":{"x":0.833,"y":1},"o":{"x":0.167,"y":0},"t":41,"s":[101,25.889],"to":[0,2.935],"ti":[0,2.5]},{"i":{"x":0.667,"y":1},"o":{"x":0.333,"y":0},"t":45,"s":[101,20.5],"to":[0,-2.5],"ti":[0,-0.898]},{"i":{"x":0.667,"y":1},"o":{"x":0.333,"y":0},"t":49,"s":[101,10.889],"to":[0,0.898],"ti":[0,-1.602]},{"i":{"x":0.833,"y":1},"o":{"x":0.167,"y":0},"t":53,"s":[101,25.889],"to":[0,1.602],"ti":[0,2.5]},{"i":{"x":0.667,"y":1},"o":{"x":0.333,"y":0},"t":57,"s":[101,20.5],"to":[0,-2.5],"ti":[0,-0.898]},{"i":{"x":0.667,"y":1},"o":{"x":0.333,"y":0},"t":61,"s":[101,10.889],"to":[0,0.898],"ti":[0,-2.5]},{"t":65.0000026475043,"s":[101,25.889]}],"ix":2},"a":{"a":1,"k":[{"i":{"x":0.667,"y":1},"o":{"x":0.333,"y":0},"t":33,"s":[0,0],"to":[0,-2.333],"ti":[0,0]},{"i":{"x":0.667,"y":1},"o":{"x":0.333,"y":0},"t":37,"s":[0,-14],"to":[0,0],"ti":[0,-2.333]},{"i":{"x":0.833,"y":0.833},"o":{"x":0.333,"y":0.333},"t":41,"s":[0,0],"to":[0,0],"ti":[0,0]},{"i":{"x":0.667,"y":1},"o":{"x":0.333,"y":0},"t":45,"s":[0,0],"to":[0,-2.333],"ti":[0,0]},{"i":{"x":0.667,"y":1},"o":{"x":0.333,"y":0},"t":49,"s":[0,-14],"to":[0,0],"ti":[0,-2.333]},{"i":{"x":0.833,"y":0.833},"o":{"x":0.333,"y":0.333},"t":53,"s":[0,0],"to":[0,0],"ti":[0,0]},{"i":{"x":0.667,"y":1},"o":{"x":0.333,"y":0},"t":57,"s":[0,0],"to":[0,-2.333],"ti":[0,0]},{"i":{"x":0.667,"y":1},"o":{"x":0.333,"y":0},"t":61,"s":[0,-14],"to":[0,0],"ti":[0,-2.333]},{"t":65.0000026475043,"s":[0,0]}],"ix":1},"s":{"a":1,"k":[{"i":{"x":[0.833,0.833],"y":[1,1]},"o":{"x":[0.167,0.167],"y":[0,0]},"t":18,"s":[0,0]},{"i":{"x":[0.833,0.833],"y":[1,1]},"o":{"x":[0.167,0.167],"y":[0,0]},"t":26,"s":[120,120]},{"i":{"x":[0.833,0.833],"y":[1,1]},"o":{"x":[0.167,0.167],"y":[0,0]},"t":29,"s":[100,100]},{"i":{"x":[0.833,0.833],"y":[1,1]},"o":{"x":[0.167,0.167],"y":[0,0]},"t":33,"s":[100,100]},{"i":{"x":[0.833,0.833],"y":[1,1]},"o":{"x":[0.167,0.167],"y":[0,0]},"t":37,"s":[100,20]},{"i":{"x":[0.833,0.833],"y":[1,1]},"o":{"x":[0.167,0.167],"y":[0,0]},"t":41,"s":[100,100]},{"i":{"x":[0.833,0.833],"y":[1,1]},"o":{"x":[0.167,0.167],"y":[0,0]},"t":45,"s":[100,100]},{"i":{"x":[0.833,0.833],"y":[1,1]},"o":{"x":[0.167,0.167],"y":[0,0]},"t":49,"s":[100,40]},{"i":{"x":[0.833,0.833],"y":[1,1]},"o":{"x":[0.167,0.167],"y":[0,0]},"t":53,"s":[100,100]},{"i":{"x":[0.833,0.833],"y":[1,1]},"o":{"x":[0.167,0.167],"y":[0,0]},"t":57,"s":[100,100]},{"i":{"x":[0.833,0.833],"y":[1,1]},"o":{"x":[0.167,0.167],"y":[0,0]},"t":61,"s":[100,60]},{"t":65.0000026475043,"s":[100,100]}],"ix":3},"r":{"a":0,"k":0,"ix":6},"o":{"a":0,"k":100,"ix":7},"sk":{"a":0,"k":0,"ix":4},"sa":{"a":0,"k":0,"ix":5},"nm":"トランスフォーム"}],"nm":"グループ 5","np":2,"cix":2,"bm":0,"ix":4,"mn":"ADBE Vector Group","hd":false},{"ty":"gr","it":[{"ind":0,"ty":"sh","ix":1,"ks":{"a":0,"k":{"i":[[0,0],[0,0],[0,0],[0,0]],"o":[[0,0],[0,0],[0,0],[0,0]],"v":[[-16.5,-8.5],[16.5,-8.5],[16.5,8.5],[-16.5,8.5]],"c":true},"ix":2},"nm":"パス 1","mn":"ADBE Vector Shape - Group","hd":false},{"ty":"fl","c":{"a":0,"k":[0.729411764706,0.635294117647,0.501960784314,1],"ix":4},"o":{"a":0,"k":100,"ix":5},"r":1,"bm":0,"nm":"塗り 1","mn":"ADBE Vector Graphic - Fill","hd":false},{"ty":"tr","p":{"a":0,"k":[111.5,48.5],"ix":2},"a":{"a":0,"k":[0,0],"ix":1},"s":{"a":1,"k":[{"i":{"x":[0.667,0.667],"y":[1,1]},"o":{"x":[0.333,0.333],"y":[0,0]},"t":20,"s":[0,0]},{"i":{"x":[0.667,0.667],"y":[1,1]},"o":{"x":[0.333,0.333],"y":[0,0]},"t":28,"s":[120,120]},{"t":31.0000012626559,"s":[100,100]}],"ix":3},"r":{"a":0,"k":0,"ix":6},"o":{"a":0,"k":100,"ix":7},"sk":{"a":0,"k":0,"ix":4},"sa":{"a":0,"k":0,"ix":5},"nm":"トランスフォーム"}],"nm":"グループ 4","np":2,"cix":2,"bm":0,"ix":5,"mn":"ADBE Vector Group","hd":false},{"ty":"gr","it":[{"ind":0,"ty":"sh","ix":1,"ks":{"a":0,"k":{"i":[[-11.322,0],[0,-11.322],[11.322,0],[0,11.322]],"o":[[11.322,0],[0,11.322],[-11.322,0],[0,-11.322]],"v":[[0,-20.5],[20.5,0],[0,20.5],[-20.5,0]],"c":true},"ix":2},"nm":"パス 1","mn":"ADBE Vector Shape - Group","hd":false},{"ty":"fl","c":{"a":0,"k":[0.435294147566,0.388235324037,0.337254901961,1],"ix":4},"o":{"a":0,"k":100,"ix":5},"r":1,"bm":0,"nm":"塗り 1","mn":"ADBE Vector Graphic - Fill","hd":false},{"ty":"tr","p":{"a":1,"k":[{"i":{"x":0.667,"y":1},"o":{"x":0.333,"y":0},"t":38,"s":[153.5,36.5],"to":[3.333,0],"ti":[0,0]},{"i":{"x":0.667,"y":1},"o":{"x":0.333,"y":0},"t":49,"s":[173.5,36.5],"to":[0,0],"ti":[3.333,0]},{"t":54.0000021994651,"s":[153.5,36.5]}],"ix":2},"a":{"a":0,"k":[0,0],"ix":1},"s":{"a":1,"k":[{"i":{"x":[0.667,0.667],"y":[1,1]},"o":{"x":[0.333,0.333],"y":[0,0]},"t":25,"s":[0,0]},{"i":{"x":[0.667,0.667],"y":[1,1]},"o":{"x":[0.333,0.333],"y":[0,0]},"t":32,"s":[120,120]},{"t":35.0000014255792,"s":[100,100]}],"ix":3},"r":{"a":0,"k":0,"ix":6},"o":{"a":0,"k":100,"ix":7},"sk":{"a":0,"k":0,"ix":4},"sa":{"a":0,"k":0,"ix":5},"nm":"トランスフォーム"}],"nm":"グループ 9","np":2,"cix":2,"bm":0,"ix":6,"mn":"ADBE Vector Group","hd":false},{"ty":"gr","it":[{"ind":0,"ty":"sh","ix":1,"ks":{"a":0,"k":{"i":[[0,0],[0,0],[0,0],[0,0]],"o":[[0,0],[0,0],[0,0],[0,0]],"v":[[-20,-11.5],[20,-11.5],[20,11.5],[-20,11.5]],"c":true},"ix":2},"nm":"パス 1","mn":"ADBE Vector Shape - Group","hd":false},{"ty":"fl","c":{"a":0,"k":[0.435294147566,0.388235324037,0.337254901961,1],"ix":4},"o":{"a":0,"k":100,"ix":5},"r":1,"bm":0,"nm":"塗り 1","mn":"ADBE Vector Graphic - Fill","hd":false},{"ty":"tr","p":{"a":0,"k":[49,77.5],"ix":2},"a":{"a":0,"k":[0,0],"ix":1},"s":{"a":1,"k":[{"i":{"x":[0.833,0.833],"y":[1,1]},"o":{"x":[0.333,0.333],"y":[0,0]},"t":35,"s":[0,0]},{"i":{"x":[0.833,0.833],"y":[1,1]},"o":{"x":[0.167,0.167],"y":[0,0]},"t":44,"s":[120,120]},{"t":47.0000019143492,"s":[100,100]}],"ix":3},"r":{"a":0,"k":0,"ix":6},"o":{"a":0,"k":100,"ix":7},"sk":{"a":0,"k":0,"ix":4},"sa":{"a":0,"k":0,"ix":5},"nm":"トランスフォーム"}],"nm":"グループ 3","np":2,"cix":2,"bm":0,"ix":7,"mn":"ADBE Vector Group","hd":false},{"ty":"gr","it":[{"ind":0,"ty":"sh","ix":1,"ks":{"a":0,"k":{"i":[[0,0],[1.005,-2.427],[1.857,-1.857],[2.426,-1.006],[2.626,0],[2.427,1.005],[1.857,1.857],[1.005,2.426],[0,2.626],[0,0]],"o":[[0,2.626],[-1.005,2.426],[-1.857,1.857],[-2.427,1.005],[-2.626,0],[-2.426,-1.006],[-1.857,-1.857],[-1.005,-2.427],[0,0],[0,0]],"v":[[20,-10],[18.478,-2.346],[14.142,4.142],[7.654,8.478],[0,10],[-7.654,8.478],[-14.142,4.142],[-18.478,-2.346],[-20,-10],[0,-10]],"c":true},"ix":2},"nm":"パス 1","mn":"ADBE Vector Shape - Group","hd":false},{"ty":"fl","c":{"a":0,"k":[0.674509803922,0.466666696586,0.274509803922,1],"ix":4},"o":{"a":0,"k":100,"ix":5},"r":1,"bm":0,"nm":"塗り 1","mn":"ADBE Vector Graphic - Fill","hd":false},{"ty":"tr","p":{"a":0,"k":[49,99],"ix":2},"a":{"a":0,"k":[0,0],"ix":1},"s":{"a":1,"k":[{"i":{"x":[0.833,0.833],"y":[1,1]},"o":{"x":[0.167,0.167],"y":[0,0]},"t":36,"s":[0,0]},{"i":{"x":[0.833,0.833],"y":[1,1]},"o":{"x":[0.167,0.167],"y":[0,0]},"t":45,"s":[120,120]},{"i":{"x":[0.833,0.833],"y":[1,1]},"o":{"x":[0.167,0.167],"y":[0,0]},"t":48,"s":[100,100]},{"i":{"x":[0.833,0.833],"y":[1,1]},"o":{"x":[0.167,0.167],"y":[0,0]},"t":52,"s":[110,110]},{"i":{"x":[0.833,0.833],"y":[1,1]},"o":{"x":[0.167,0.167],"y":[0,0]},"t":56,"s":[100,100]},{"i":{"x":[0.833,0.833],"y":[1,1]},"o":{"x":[0.167,0.167],"y":[0,0]},"t":60,"s":[105,105]},{"t":64.0000026067734,"s":[100,100]}],"ix":3},"r":{"a":0,"k":0,"ix":6},"o":{"a":0,"k":100,"ix":7},"sk":{"a":0,"k":0,"ix":4},"sa":{"a":0,"k":0,"ix":5},"nm":"トランスフォーム"}],"nm":"グループ 7","np":2,"cix":2,"bm":0,"ix":8,"mn":"ADBE Vector Group","hd":false},{"ty":"gr","it":[{"ind":0,"ty":"sh","ix":1,"ks":{"a":0,"k":{"i":[[0,0],[0,0],[0,0]],"o":[[0,0],[0,0],[0,0]],"v":[[-18,-21],[18,21],[-18,21]],"c":true},"ix":2},"nm":"パス 1","mn":"ADBE Vector Shape - Group","hd":false},{"ty":"fl","c":{"a":0,"k":[0.729411764706,0.635294117647,0.501960784314,1],"ix":4},"o":{"a":0,"k":100,"ix":5},"r":1,"bm":0,"nm":"塗り 1","mn":"ADBE Vector Graphic - Fill","hd":false},{"ty":"tr","p":{"a":0,"k":[96,86],"ix":2},"a":{"a":0,"k":[0,0],"ix":1},"s":{"a":1,"k":[{"i":{"x":[0.833,0.833],"y":[1,1]},"o":{"x":[0.167,0.167],"y":[0,0]},"t":48,"s":[0,0]},{"i":{"x":[0.833,0.833],"y":[1,1]},"o":{"x":[0.167,0.167],"y":[0,0]},"t":57,"s":[120,120]},{"t":60.0000024438501,"s":[100,100]}],"ix":3},"r":{"a":0,"k":0,"ix":6},"o":{"a":0,"k":100,"ix":7},"sk":{"a":0,"k":0,"ix":4},"sa":{"a":0,"k":0,"ix":5},"nm":"トランスフォーム"}],"nm":"グループ 1","np":2,"cix":2,"bm":0,"ix":9,"mn":"ADBE Vector Group","hd":false},{"ty":"gr","it":[{"ind":0,"ty":"sh","ix":1,"ks":{"a":0,"k":{"i":[[0,0],[0,0],[0,0],[0,0]],"o":[[0,0],[0,0],[0,0],[0,0]],"v":[[-6,-21.5],[6,-21.5],[6,21.5],[-6,21.5]],"c":true},"ix":2},"nm":"パス 1","mn":"ADBE Vector Shape - Group","hd":false},{"ty":"fl","c":{"a":0,"k":[0.435294147566,0.388235324037,0.337254901961,1],"ix":4},"o":{"a":0,"k":100,"ix":5},"r":1,"bm":0,"nm":"塗り 1","mn":"ADBE Vector Graphic - Fill","hd":false},{"ty":"tr","p":{"a":0,"k":[114.143,106.473],"ix":2},"a":{"a":1,"k":[{"i":{"x":0.667,"y":1},"o":{"x":0.333,"y":0},"t":54,"s":[0,0],"to":[1.024,3.495],"ti":[-1.024,-3.495]},{"t":62.0000025253118,"s":[6.143,20.973]}],"ix":1},"s":{"a":1,"k":[{"i":{"x":[0.833,0.833],"y":[1,1]},"o":{"x":[0.167,0.167],"y":[0,0]},"t":54,"s":[0,0]},{"i":{"x":[0.833,0.833],"y":[1,1]},"o":{"x":[0.167,0.167],"y":[0,0]},"t":62,"s":[120,120]},{"t":65.0000026475043,"s":[100,100]}],"ix":3},"r":{"a":1,"k":[{"i":{"x":[0.667],"y":[1]},"o":{"x":[0.167],"y":[0]},"t":66,"s":[0]},{"i":{"x":[0.833],"y":[1]},"o":{"x":[0.333],"y":[0]},"t":73,"s":[13]},{"t":78.0000031770051,"s":[0]}],"ix":6},"o":{"a":0,"k":100,"ix":7},"sk":{"a":0,"k":0,"ix":4},"sa":{"a":0,"k":0,"ix":5},"nm":"トランスフォーム"}],"nm":"グループ 2","np":2,"cix":2,"bm":0,"ix":10,"mn":"ADBE Vector Group","hd":false},{"ty":"gr","it":[{"ind":0,"ty":"sh","ix":1,"ks":{"a":0,"k":{"i":[[-11.322,0],[0,-11.322],[11.322,0],[0,11.322]],"o":[[11.322,0],[0,11.322],[-11.322,0],[0,-11.322]],"v":[[0,-20.5],[20.5,0],[0,20.5],[-20.5,0]],"c":true},"ix":2},"nm":"パス 1","mn":"ADBE Vector Shape - Group","hd":false},{"ty":"fl","c":{"a":0,"k":[0.729411764706,0.635294117647,0.501960784314,1],"ix":4},"o":{"a":0,"k":100,"ix":5},"r":1,"bm":0,"nm":"塗り 1","mn":"ADBE Vector Graphic - Fill","hd":false},{"ty":"tr","p":{"a":1,"k":[{"i":{"x":0.667,"y":1},"o":{"x":0.333,"y":0},"t":82,"s":[142.5,85.5],"to":[0.5,0],"ti":[0,0]},{"i":{"x":0.667,"y":1},"o":{"x":0.333,"y":0},"t":84,"s":[145.5,85.5],"to":[0,0],"ti":[1,0]},{"i":{"x":0.667,"y":1},"o":{"x":0.333,"y":0},"t":86,"s":[142.5,85.5],"to":[-1,0],"ti":[0,0]},{"i":{"x":0.667,"y":1},"o":{"x":0.333,"y":0},"t":88,"s":[139.5,85.5],"to":[0,0],"ti":[-0.5,0]},{"t":90.0000036657751,"s":[142.5,85.5]}],"ix":2},"a":{"a":0,"k":[0,0],"ix":1},"s":{"a":1,"k":[{"i":{"x":[0.833,0.833],"y":[1,1]},"o":{"x":[0.167,0.167],"y":[0,0]},"t":74,"s":[0,0]},{"i":{"x":[0.833,0.833],"y":[1,1]},"o":{"x":[0.167,0.167],"y":[0,0]},"t":80,"s":[120,120]},{"t":82.0000033399285,"s":[100,100]}],"ix":3},"r":{"a":0,"k":0,"ix":6},"o":{"a":0,"k":100,"ix":7},"sk":{"a":0,"k":0,"ix":4},"sa":{"a":0,"k":0,"ix":5},"nm":"トランスフォーム"}],"nm":"グループ 10","np":2,"cix":2,"bm":0,"ix":11,"mn":"ADBE Vector Group","hd":false}],"ip":0,"op":899.000036617021,"st":0,"ct":1,"bm":0}],"markers":[]}